{
  "swagger": "2.0",
  "info": {
    "title": "FileVault API",
    "version": "1.0.0",
    "description": "\n# 🔐 FileVault - Secure Cloud File Storage API\n\n## Overview\nFileVault is an enterprise-grade secure file storage solution with advanced authentication and AWS S3 integration.\n\n## Features\n- 🔒 JWT-based authentication with email verification\n- 📁 Secure file upload/download with AWS S3\n- 🛡️ Rate limiting and security middleware\n- 📊 Comprehensive logging and monitoring\n- 🔗 Shareable links with expiration controls\n\n## Authentication\nMost endpoints require a Bearer token in the Authorization header:\n```\nAuthorization: Bearer <your-jwt-token>\n```\n\n## Rate Limits\n- Auth endpoints: 10 requests per 15 minutes\n- File operations: 100 requests per 15 minutes\n- Anonymous uploads: 5 requests per minute\n\n## File Upload Constraints\n- Maximum file size: 5GB\n- Supported formats: Images, Documents, Archives, Media\n- File type validation enforced\n    ",
    "contact": {
      "name": "Hariom Virkhare",
      "email": "hariomvirkhare02@gmail.com",
      "url": "https://github.com/hariomop12"
    },
    "license": {
      "name": "ISC",
      "url": "https://opensource.org/licenses/ISC"
    }
  },
  "host": "localhost:3000",
  "basePath": "/",
  "tags": [
    {
      "name": "Authentication",
      "description": "User authentication and account management"
    },
    {
      "name": "Anonymous Files",
      "description": "File operations without authentication"
    },
    {
      "name": "User Files",
      "description": "Authenticated user file management"
    },
    {
      "name": "Health",
      "description": "API health and status endpoints"
    }
  ],
  "schemes": [
    "http",
    "https"
  ],
  "securityDefinitions": {
    "bearerAuth": {
      "type": "http",
      "scheme": "bearer",
      "bearerFormat": "JWT"
    }
  },
  "consumes": [
    "application/json",
    "multipart/form-data"
  ],
  "produces": [
    "application/json"
  ],
  "paths": {
    "/": {
      "get": {
        "description": "",
        "responses": {
          "200": {
            "description": "OK"
          }
        }
      }
    },
    "/health": {
      "get": {
        "description": "",
        "responses": {
          "200": {
            "description": "OK"
          }
        }
      }
    },
    "/api/v1/auth/signup": {
      "post": {
        "description": "",
        "parameters": [
          {
            "name": "body",
            "in": "body",
            "schema": {
              "type": "object",
              "properties": {
                "name": {
                  "example": "any"
                },
                "email": {
                  "example": "any"
                },
                "password": {
                  "example": "any"
                }
              }
            }
          }
        ],
        "responses": {
          "201": {
            "description": "Created"
          },
          "400": {
            "description": "Bad Request"
          },
          "500": {
            "description": "Internal Server Error"
          }
        }
      }
    },
    "/api/v1/auth/login": {
      "post": {
        "description": "",
        "parameters": [
          {
            "name": "body",
            "in": "body",
            "schema": {
              "type": "object",
              "properties": {
                "email": {
                  "example": "any"
                },
                "password": {
                  "example": "any"
                }
              }
            }
          }
        ],
        "responses": {
          "200": {
            "description": "OK"
          },
          "400": {
            "description": "Bad Request"
          },
          "401": {
            "description": "Unauthorized"
          },
          "500": {
            "description": "Internal Server Error"
          }
        }
      }
    },
    "/api/v1/auth/verify-email": {
      "get": {
        "description": "",
        "parameters": [
          {
            "name": "token",
            "in": "query",
            "type": "string"
          }
        ],
        "responses": {
          "200": {
            "description": "OK"
          },
          "400": {
            "description": "Bad Request"
          },
          "500": {
            "description": "Internal Server Error"
          }
        }
      }
    },
    "/api/v1/auth/forgot-password": {
      "post": {
        "description": "",
        "parameters": [
          {
            "name": "body",
            "in": "body",
            "schema": {
              "type": "object",
              "properties": {
                "email": {
                  "example": "any"
                }
              }
            }
          }
        ],
        "responses": {
          "200": {
            "description": "OK"
          },
          "400": {
            "description": "Bad Request"
          },
          "500": {
            "description": "Internal Server Error"
          }
        }
      }
    },
    "/api/v1/auth/reset-password": {
      "post": {
        "description": "",
        "parameters": [
          {
            "name": "body",
            "in": "body",
            "schema": {
              "type": "object",
              "properties": {
                "token": {
                  "example": "any"
                },
                "password": {
                  "example": "any"
                }
              }
            }
          }
        ],
        "responses": {
          "200": {
            "description": "OK"
          },
          "400": {
            "description": "Bad Request"
          },
          "500": {
            "description": "Internal Server Error"
          }
        }
      }
    },
    "/api/v1/auth/resend-verification": {
      "post": {
        "description": "",
        "parameters": [
          {
            "name": "body",
            "in": "body",
            "schema": {
              "type": "object",
              "properties": {
                "email": {
                  "example": "any"
                }
              }
            }
          }
        ],
        "responses": {
          "200": {
            "description": "OK"
          },
          "400": {
            "description": "Bad Request"
          },
          "500": {
            "description": "Internal Server Error"
          }
        }
      }
    },
    "/api/v1/files/upload": {
      "post": {
        "tags": [
          "Anonymous Files"
        ],
        "summary": "Anonymous file upload",
        "description": "Upload a file without authentication (public access)",
        "consumes": [
          "multipart/form-data"
        ],
        "parameters": [
          {
            "name": "file",
            "in": "formData",
            "type": "file",
            "required": true,
            "description": "File to upload (max 5GB)"
          }
        ],
        "responses": {
          "200": {
            "description": "File uploaded successfully",
            "schema": {
              "$ref": "#/definitions/ApiResponse"
            }
          },
          "400": {
            "description": "Bad request",
            "schema": {
              "$ref": "#/definitions/ErrorResponse"
            }
          }
        }
      }
    },
    "/api/v1/files/download": {
      "post": {
        "tags": [
          "Anonymous Files"
        ],
        "summary": "Anonymous file download",
        "description": "Download a file using file ID and secret key",
        "parameters": [
          {
            "name": "body",
            "in": "body",
            "required": true,
            "schema": {
              "type": "object",
              "properties": {
                "type": {
                  "type": "string",
                  "example": "object"
                },
                "required": {
                  "type": "array",
                  "example": [
                    "file_id",
                    "secret_key"
                  ],
                  "items": {
                    "type": "string"
                  }
                },
                "properties": {
                  "type": "object",
                  "properties": {
                    "file_id": {
                      "type": "object",
                      "properties": {
                        "type": {
                          "type": "string",
                          "example": "string"
                        },
                        "example": {
                          "type": "string",
                          "example": "abc123def456"
                        }
                      }
                    },
                    "secret_key": {
                      "type": "object",
                      "properties": {
                        "type": {
                          "type": "string",
                          "example": "string"
                        },
                        "example": {
                          "type": "string",
                          "example": "xyz789secret"
                        }
                      }
                    }
                  }
                }
              }
            }
          }
        ],
        "responses": {
          "200": {
            "description": "Download link generated successfully",
            "schema": {
              "$ref": "#/definitions/ApiResponse"
            }
          },
          "400": {
            "description": "Bad Request"
          },
          "404": {
            "description": "Not Found"
          },
          "500": {
            "description": "Internal Server Error"
          }
        }
      }
    },
    "/api/v1/upload": {
      "post": {
        "description": "",
        "parameters": [
          {
            "name": "authorization",
            "in": "header",
            "type": "string"
          }
        ],
        "responses": {
          "201": {
            "description": "Created"
          },
          "400": {
            "description": "Bad Request"
          },
          "401": {
            "description": "Unauthorized"
          },
          "500": {
            "description": "Internal Server Error"
          }
        }
      }
    },
    "/api/v1/files": {
      "get": {
        "description": "",
        "parameters": [
          {
            "name": "authorization",
            "in": "header",
            "type": "string"
          }
        ],
        "responses": {
          "200": {
            "description": "OK"
          },
          "401": {
            "description": "Unauthorized"
          },
          "500": {
            "description": "Internal Server Error"
          }
        }
      }
    },
    "/api/v1/files/{id}": {
      "get": {
        "description": "",
        "parameters": [
          {
            "name": "id",
            "in": "path",
            "required": true,
            "type": "string"
          },
          {
            "name": "authorization",
            "in": "header",
            "type": "string"
          },
          {
            "name": "x-forwarded-for",
            "in": "header",
            "type": "string"
          }
        ],
        "responses": {
          "200": {
            "description": "OK"
          },
          "401": {
            "description": "Unauthorized"
          },
          "404": {
            "description": "Not Found"
          },
          "500": {
            "description": "Internal Server Error"
          }
        }
      },
      "delete": {
        "description": "",
        "parameters": [
          {
            "name": "id",
            "in": "path",
            "required": true,
            "type": "string"
          },
          {
            "name": "authorization",
            "in": "header",
            "type": "string"
          }
        ],
        "responses": {
          "200": {
            "description": "OK"
          },
          "401": {
            "description": "Unauthorized"
          },
          "404": {
            "description": "Not Found"
          },
          "500": {
            "description": "Internal Server Error"
          }
        }
      }
    },
    "/api/v1/download/{id}": {
      "get": {
        "description": "",
        "parameters": [
          {
            "name": "id",
            "in": "path",
            "required": true,
            "type": "string"
          },
          {
            "name": "authorization",
            "in": "header",
            "type": "string"
          }
        ],
        "responses": {
          "200": {
            "description": "OK"
          },
          "401": {
            "description": "Unauthorized"
          },
          "404": {
            "description": "Not Found"
          },
          "500": {
            "description": "Internal Server Error"
          }
        }
      }
    },
    "/api/v1/files/{id}/share": {
      "post": {
        "description": "",
        "parameters": [
          {
            "name": "id",
            "in": "path",
            "required": true,
            "type": "string"
          },
          {
            "name": "authorization",
            "in": "header",
            "type": "string"
          }
        ],
        "responses": {
          "200": {
            "description": "OK"
          },
          "401": {
            "description": "Unauthorized"
          },
          "404": {
            "description": "Not Found"
          },
          "500": {
            "description": "Internal Server Error"
          }
        }
      }
    },
    "/signup": {
      "post": {
        "description": "",
        "parameters": [
          {
            "name": "body",
            "in": "body",
            "schema": {
              "type": "object",
              "properties": {
                "name": {
                  "example": "any"
                },
                "email": {
                  "example": "any"
                },
                "password": {
                  "example": "any"
                }
              }
            }
          }
        ],
        "responses": {
          "201": {
            "description": "Created"
          },
          "400": {
            "description": "Bad Request"
          },
          "500": {
            "description": "Internal Server Error"
          }
        }
      }
    },
    "/login": {
      "post": {
        "description": "",
        "parameters": [
          {
            "name": "body",
            "in": "body",
            "schema": {
              "type": "object",
              "properties": {
                "email": {
                  "example": "any"
                },
                "password": {
                  "example": "any"
                }
              }
            }
          }
        ],
        "responses": {
          "200": {
            "description": "OK"
          },
          "400": {
            "description": "Bad Request"
          },
          "401": {
            "description": "Unauthorized"
          },
          "500": {
            "description": "Internal Server Error"
          }
        }
      }
    },
    "/verify-email": {
      "get": {
        "description": "",
        "parameters": [
          {
            "name": "token",
            "in": "query",
            "type": "string"
          }
        ],
        "responses": {
          "200": {
            "description": "OK"
          },
          "400": {
            "description": "Bad Request"
          },
          "500": {
            "description": "Internal Server Error"
          }
        }
      }
    },
    "/forgot-password": {
      "post": {
        "description": "",
        "parameters": [
          {
            "name": "body",
            "in": "body",
            "schema": {
              "type": "object",
              "properties": {
                "email": {
                  "example": "any"
                }
              }
            }
          }
        ],
        "responses": {
          "200": {
            "description": "OK"
          },
          "400": {
            "description": "Bad Request"
          },
          "500": {
            "description": "Internal Server Error"
          }
        }
      }
    },
    "/reset-password": {
      "post": {
        "description": "",
        "parameters": [
          {
            "name": "body",
            "in": "body",
            "schema": {
              "type": "object",
              "properties": {
                "token": {
                  "example": "any"
                },
                "password": {
                  "example": "any"
                }
              }
            }
          }
        ],
        "responses": {
          "200": {
            "description": "OK"
          },
          "400": {
            "description": "Bad Request"
          },
          "500": {
            "description": "Internal Server Error"
          }
        }
      }
    },
    "/resend-verification": {
      "post": {
        "description": "",
        "parameters": [
          {
            "name": "body",
            "in": "body",
            "schema": {
              "type": "object",
              "properties": {
                "email": {
                  "example": "any"
                }
              }
            }
          }
        ],
        "responses": {
          "200": {
            "description": "OK"
          },
          "400": {
            "description": "Bad Request"
          },
          "500": {
            "description": "Internal Server Error"
          }
        }
      }
    },
    "/upload": {
      "post": {
        "description": "",
        "parameters": [
          {
            "name": "authorization",
            "in": "header",
            "type": "string"
          }
        ],
        "responses": {
          "200": {
            "description": "File uploaded successfully",
            "schema": {
              "$ref": "#/definitions/ApiResponse"
            }
          },
          "201": {
            "description": "Created"
          },
          "400": {
            "description": "Bad Request",
            "schema": {
              "$ref": "#/definitions/ErrorResponse"
            }
          },
          "401": {
            "description": "Unauthorized"
          },
          "500": {
            "description": "Internal Server Error"
          }
        }
      }
    },
    "/download": {
      "post": {
        "tags": [
          "Anonymous Files"
        ],
        "summary": "Anonymous file download",
        "description": "Download a file using file ID and secret key",
        "parameters": [
          {
            "name": "body",
            "in": "body",
            "required": true,
            "schema": {
              "type": "object",
              "properties": {
                "type": {
                  "type": "string",
                  "example": "object"
                },
                "required": {
                  "type": "array",
                  "example": [
                    "file_id",
                    "secret_key"
                  ],
                  "items": {
                    "type": "string"
                  }
                },
                "properties": {
                  "type": "object",
                  "properties": {
                    "file_id": {
                      "type": "object",
                      "properties": {
                        "type": {
                          "type": "string",
                          "example": "string"
                        },
                        "example": {
                          "type": "string",
                          "example": "abc123def456"
                        }
                      }
                    },
                    "secret_key": {
                      "type": "object",
                      "properties": {
                        "type": {
                          "type": "string",
                          "example": "string"
                        },
                        "example": {
                          "type": "string",
                          "example": "xyz789secret"
                        }
                      }
                    }
                  }
                }
              }
            }
          }
        ],
        "responses": {
          "200": {
            "description": "Download link generated successfully",
            "schema": {
              "$ref": "#/definitions/ApiResponse"
            }
          },
          "400": {
            "description": "Bad Request"
          },
          "404": {
            "description": "Not Found"
          },
          "500": {
            "description": "Internal Server Error"
          }
        }
      }
    },
    "/files": {
      "get": {
        "description": "",
        "parameters": [
          {
            "name": "authorization",
            "in": "header",
            "type": "string"
          }
        ],
        "responses": {
          "200": {
            "description": "OK"
          },
          "401": {
            "description": "Unauthorized"
          },
          "500": {
            "description": "Internal Server Error"
          }
        }
      }
    },
    "/files/{id}": {
      "get": {
        "description": "",
        "parameters": [
          {
            "name": "id",
            "in": "path",
            "required": true,
            "type": "string"
          },
          {
            "name": "authorization",
            "in": "header",
            "type": "string"
          },
          {
            "name": "x-forwarded-for",
            "in": "header",
            "type": "string"
          }
        ],
        "responses": {
          "200": {
            "description": "OK"
          },
          "401": {
            "description": "Unauthorized"
          },
          "404": {
            "description": "Not Found"
          },
          "500": {
            "description": "Internal Server Error"
          }
        }
      },
      "delete": {
        "description": "",
        "parameters": [
          {
            "name": "id",
            "in": "path",
            "required": true,
            "type": "string"
          },
          {
            "name": "authorization",
            "in": "header",
            "type": "string"
          }
        ],
        "responses": {
          "200": {
            "description": "OK"
          },
          "401": {
            "description": "Unauthorized"
          },
          "404": {
            "description": "Not Found"
          },
          "500": {
            "description": "Internal Server Error"
          }
        }
      }
    },
    "/download/{id}": {
      "get": {
        "description": "",
        "parameters": [
          {
            "name": "id",
            "in": "path",
            "required": true,
            "type": "string"
          },
          {
            "name": "authorization",
            "in": "header",
            "type": "string"
          }
        ],
        "responses": {
          "200": {
            "description": "OK"
          },
          "401": {
            "description": "Unauthorized"
          },
          "404": {
            "description": "Not Found"
          },
          "500": {
            "description": "Internal Server Error"
          }
        }
      }
    },
    "/files/{id}/share": {
      "post": {
        "description": "",
        "parameters": [
          {
            "name": "id",
            "in": "path",
            "required": true,
            "type": "string"
          },
          {
            "name": "authorization",
            "in": "header",
            "type": "string"
          }
        ],
        "responses": {
          "200": {
            "description": "OK"
          },
          "401": {
            "description": "Unauthorized"
          },
          "404": {
            "description": "Not Found"
          },
          "500": {
            "description": "Internal Server Error"
          }
        }
      }
    }
  },
  "definitions": {
    "User": {
      "type": "object",
      "properties": {
        "type": {
          "type": "string",
          "example": "object"
        },
        "properties": {
          "type": "object",
          "properties": {
            "id": {
              "type": "object",
              "properties": {
                "type": {
                  "type": "string",
                  "example": "integer"
                },
                "description": {
                  "type": "string",
                  "example": "User ID"
                }
              }
            },
            "name": {
              "type": "object",
              "properties": {
                "type": {
                  "type": "string",
                  "example": "string"
                },
                "description": {
                  "type": "string",
                  "example": "User full name"
                }
              }
            },
            "email": {
              "type": "object",
              "properties": {
                "type": {
                  "type": "string",
                  "example": "string"
                },
                "format": {
                  "type": "string",
                  "example": "email"
                },
                "description": {
                  "type": "string",
                  "example": "User email address"
                }
              }
            },
            "email_verified": {
              "type": "object",
              "properties": {
                "type": {
                  "type": "string",
                  "example": "boolean"
                },
                "description": {
                  "type": "string",
                  "example": "Email verification status"
                }
              }
            },
            "storage_quota": {
              "type": "object",
              "properties": {
                "type": {
                  "type": "string",
                  "example": "integer"
                },
                "description": {
                  "type": "string",
                  "example": "Storage quota in bytes"
                }
              }
            },
            "created_at": {
              "type": "object",
              "properties": {
                "type": {
                  "type": "string",
                  "example": "string"
                },
                "format": {
                  "type": "string",
                  "example": "date-time"
                },
                "description": {
                  "type": "string",
                  "example": "Account creation timestamp"
                }
              }
            }
          }
        }
      }
    },
    "File": {
      "type": "object",
      "properties": {
        "type": {
          "type": "string",
          "example": "object"
        },
        "properties": {
          "type": "object",
          "properties": {
            "id": {
              "type": "object",
              "properties": {
                "type": {
                  "type": "string",
                  "example": "integer"
                },
                "description": {
                  "type": "string",
                  "example": "File ID"
                }
              }
            },
            "filename": {
              "type": "object",
              "properties": {
                "type": {
                  "type": "string",
                  "example": "string"
                },
                "description": {
                  "type": "string",
                  "example": "Original filename"
                }
              }
            },
            "file_path": {
              "type": "object",
              "properties": {
                "type": {
                  "type": "string",
                  "example": "string"
                },
                "description": {
                  "type": "string",
                  "example": "File storage path"
                }
              }
            },
            "file_size": {
              "type": "object",
              "properties": {
                "type": {
                  "type": "string",
                  "example": "integer"
                },
                "description": {
                  "type": "string",
                  "example": "File size in bytes"
                }
              }
            },
            "mime_type": {
              "type": "object",
              "properties": {
                "type": {
                  "type": "string",
                  "example": "string"
                },
                "description": {
                  "type": "string",
                  "example": "File MIME type"
                }
              }
            },
            "uploaded_at": {
              "type": "object",
              "properties": {
                "type": {
                  "type": "string",
                  "example": "string"
                },
                "format": {
                  "type": "string",
                  "example": "date-time"
                },
                "description": {
                  "type": "string",
                  "example": "Upload timestamp"
                }
              }
            },
            "user_id": {
              "type": "object",
              "properties": {
                "type": {
                  "type": "string",
                  "example": "integer"
                },
                "description": {
                  "type": "string",
                  "example": "Owner user ID (null for anonymous)"
                }
              }
            }
          }
        }
      }
    },
    "LoginRequest": {
      "type": "object",
      "properties": {
        "type": {
          "type": "string",
          "example": "object"
        },
        "required": {
          "type": "array",
          "example": [
            "email",
            "password"
          ],
          "items": {
            "type": "string"
          }
        },
        "properties": {
          "type": "object",
          "properties": {
            "email": {
              "type": "object",
              "properties": {
                "type": {
                  "type": "string",
                  "example": "string"
                },
                "format": {
                  "type": "string",
                  "example": "email"
                },
                "example": {
                  "type": "string",
                  "example": "user@example.com"
                }
              }
            },
            "password": {
              "type": "object",
              "properties": {
                "type": {
                  "type": "string",
                  "example": "string"
                },
                "minLength": {
                  "type": "number",
                  "example": 8
                },
                "example": {
                  "type": "string",
                  "example": "password123"
                }
              }
            }
          }
        }
      }
    },
    "SignupRequest": {
      "type": "object",
      "properties": {
        "type": {
          "type": "string",
          "example": "object"
        },
        "required": {
          "type": "array",
          "example": [
            "name",
            "email",
            "password"
          ],
          "items": {
            "type": "string"
          }
        },
        "properties": {
          "type": "object",
          "properties": {
            "name": {
              "type": "object",
              "properties": {
                "type": {
                  "type": "string",
                  "example": "string"
                },
                "example": {
                  "type": "string",
                  "example": "John Doe"
                }
              }
            },
            "email": {
              "type": "object",
              "properties": {
                "type": {
                  "type": "string",
                  "example": "string"
                },
                "format": {
                  "type": "string",
                  "example": "email"
                },
                "example": {
                  "type": "string",
                  "example": "john.doe@example.com"
                }
              }
            },
            "password": {
              "type": "object",
              "properties": {
                "type": {
                  "type": "string",
                  "example": "string"
                },
                "minLength": {
                  "type": "number",
                  "example": 8
                },
                "example": {
                  "type": "string",
                  "example": "securePassword123"
                }
              }
            }
          }
        }
      }
    },
    "ApiResponse": {
      "type": "object",
      "properties": {
        "type": {
          "type": "string",
          "example": "object"
        },
        "properties": {
          "type": "object",
          "properties": {
            "success": {
              "type": "object",
              "properties": {
                "type": {
                  "type": "string",
                  "example": "boolean"
                },
                "example": {
                  "type": "boolean",
                  "example": true
                }
              }
            },
            "message": {
              "type": "object",
              "properties": {
                "type": {
                  "type": "string",
                  "example": "string"
                },
                "description": {
                  "type": "string",
                  "example": "Response message"
                }
              }
            },
            "data": {
              "type": "object",
              "properties": {
                "type": {
                  "type": "string",
                  "example": "object"
                },
                "description": {
                  "type": "string",
                  "example": "Response data"
                }
              }
            }
          }
        }
      }
    },
    "ErrorResponse": {
      "type": "object",
      "properties": {
        "type": {
          "type": "string",
          "example": "object"
        },
        "properties": {
          "type": "object",
          "properties": {
            "success": {
              "type": "object",
              "properties": {
                "type": {
                  "type": "string",
                  "example": "boolean"
                },
                "example": {
                  "type": "boolean",
                  "example": false
                }
              }
            },
            "message": {
              "type": "object",
              "properties": {
                "type": {
                  "type": "string",
                  "example": "string"
                },
                "description": {
                  "type": "string",
                  "example": "Error message"
                }
              }
            },
            "error": {
              "type": "object",
              "properties": {
                "type": {
                  "type": "string",
                  "example": "string"
                },
                "description": {
                  "type": "string",
                  "example": "Error details"
                }
              }
            }
          }
        }
      }
    }
  }
}